Metadata-Version: 1.0
Name: aws-course-probability-dists
Version: 0.1
Summary: Gaussian and Binomial distributions
Home-page: UNKNOWN
Author: Noel Mathew
Author-email: email@something.com
License: UNKNOWN
Platform: UNKNOWN
